MANIFEST.in
setup.py
rockload/__init__.py
rockload/server.py
rockload/version.py
rockload.egg-info/PKG-INFO
rockload.egg-info/SOURCES.txt
rockload.egg-info/dependency_links.txt
rockload.egg-info/entry_points.txt
rockload.egg-info/not-zip-safe
rockload.egg-info/requires.txt
rockload.egg-info/top_level.txt
rockload/apps/__init__.py
rockload/apps/auth/__init__.py
rockload/apps/auth/handlers.py
rockload/apps/auth/models.py
rockload/apps/auth/urls.py
rockload/apps/auth/static/rockload/apps/auth/css/login.css
rockload/apps/auth/static/rockload/apps/auth/img/socials.png
rockload/apps/auth/templates/rockload/apps/auth/login.html
rockload/apps/base/__init__.py
rockload/apps/base/handlers.py
rockload/apps/base/static/rockload/apps/base/css/bootstrap-1.1.0.min.css
rockload/apps/base/static/rockload/apps/base/css/bootstrap-1.1.1.min.css
rockload/apps/base/static/rockload/apps/base/css/main.css
rockload/apps/base/static/rockload/apps/base/img/logo.png
rockload/apps/base/static/rockload/apps/base/img/logobig.png
rockload/apps/base/static/rockload/apps/base/img/question.gif
rockload/apps/base/static/rockload/apps/base/js/menu.js
rockload/apps/base/static/rockload/apps/base/js/mootools-core-1.3.2.js
rockload/apps/base/templates/rockload/apps/base/auth_base.html
rockload/apps/base/templates/rockload/apps/base/base.html
rockload/apps/main/__init__.py
rockload/apps/main/handlers.py
rockload/apps/main/models.py
rockload/apps/main/urls.py
rockload/apps/main/static/rockload/apps/main/css/funkload.css
rockload/apps/main/static/rockload/apps/main/css/index.css
rockload/apps/main/static/rockload/apps/main/css/newproject.css
rockload/apps/main/static/rockload/apps/main/css/newtest.css
rockload/apps/main/static/rockload/apps/main/css/noprojects.css
rockload/apps/main/static/rockload/apps/main/css/notests.css
rockload/apps/main/static/rockload/apps/main/css/project_details.css
rockload/apps/main/static/rockload/apps/main/css/test_details.css
rockload/apps/main/static/rockload/apps/main/img/chart.png
rockload/apps/main/static/rockload/apps/main/img/letsrock.png
rockload/apps/main/static/rockload/apps/main/js/form.js
rockload/apps/main/static/rockload/apps/main/js/index.js
