Metadata-Version: 1.0
Name: rockload
Version: 0.4.1
Summary: rockload is a load testing tool that keeps track of how your projects evolve.
Home-page: http://heynemann.github.com/rockload
Author: Bernardo Heynemann
Author-email: heynemann@gmail.com
License: MIT
Keywords: load testing benchmark funkload
Platform: UNKNOWN
Classifier: Development Status :: 3 - Alpha
Classifier: Intended Audience :: Developers
Classifier: License :: OSI Approved :: MIT License
Classifier: Natural Language :: English
Classifier: Operating System :: MacOS
Classifier: Operating System :: Microsoft :: Windows
Classifier: Operating System :: POSIX :: Linux
Classifier: Programming Language :: Python :: 2.6
Classifier: Topic :: System :: Installation/Setup
